heroku_kafka.py
heroku_kafka-3.0.0.dist-info/LICENSE.txt
heroku_kafka-3.0.0.dist-info/METADATA
heroku_kafka-3.0.0.dist-info/WHEEL
heroku_kafka-3.0.0.dist-info/top_level.txt
heroku_kafka-3.0.0.dist-info/RECORD
