Metadata-Version: 2.1
Name: heroku-kafka
Version: 3.0.0
Summary: Python kafka package for use with heroku's kafka.
Home-page: https://github.com/HubbleHQ/heroku-kafka
Author: Hubble
Author-email: dev@hubblehq.com
License: MIT
Platform: UNKNOWN
Classifier: Development Status :: 5 - Production/Stable
Classifier: License :: OSI Approved :: MIT License
Classifier: Programming Language :: Python :: 3
Classifier: Intended Audience :: Developers
License-File: LICENSE.txt
Requires-Dist: kafka-python (==1.4.6)
